{"tid":108737,"cid":7,"subCid":0,"title":"(第251GIF)雞 RaMu係雞呀！！！！！！","createTime":"2017-02-05T13:05:02.000Z","updateTime":"2017-02-05T16:36:35.000Z","uid":49391,"like":4,"dislike":0,"uniUserReply":0,"replies":[{"pid":"40e03098c41be58141575054aaed9f3af6ee4c2c","tid":108737,"uid":49391,"like":0,"dislike":0,"score":0,"citedBy":0,"replyTime":"2017-02-05T13:05:02.000Z","msg":"哈哈哈哈哈！！！！！！<br />\n<br />\n<img src=\"https://i.imag.cx/HBAL6.gif\" data-thumbnail-src=\"https://i.lih.kg/thumbnail?u=https%3A%2F%2Fi.imag.cx%2FHBAL6.gif&h=6ff0ff71&s={SIZE}\" /><br />\n<br />\n<br />\n<br />\n<img src=\"https://i.imag.cx/HBZnU.gif\" data-thumbnail-src=\"https://i.lih.kg/thumbnail?u=https%3A%2F%2Fi.imag.cx%2FHBZnU.gif&h=42dd8813&s={SIZE}\" />"},{"pid":"ecef0bda96fff0465575c32b083f4e73f0c52e78","tid":108737,"uid":49391,"like":0,"dislike":0,"score":0,"citedBy":0,"replyTime":"2017-02-05T13:05:19.000Z","msg":"<img src=\"https://i.imag.cx/HBmiu.gif\" data-thumbnail-src=\"https://i.lih.kg/thumbnail?u=https%3A%2F%2Fi.imag.cx%2FHBmiu.gif&h=55e51ecd&s={SIZE}\" /><br />\n<br />\n<br />\n<img src=\"https://i.imag.cx/HBBDm.gif\" data-thumbnail-src=\"https://i.lih.kg/thumbnail?u=https%3A%2F%2Fi.imag.cx%2FHBBDm.gif&h=375309fa&s={SIZE}\" />"},{"pid":"c9e49640ff793f27a2909772db36c031e49e852c","tid":108737,"uid":49391,"like":1,"dislike":0,"score":1,"citedBy":0,"replyTime":"2017-02-05T13:06:33.000Z","msg":"<img src=\"https://i.imag.cx/HBIZF.gif\" data-thumbnail-src=\"https://i.lih.kg/thumbnail?u=https%3A%2F%2Fi.imag.cx%2FHBIZF.gif&h=0fad15ee&s={SIZE}\" /><br />\n<br />\n<br />\n<br />\n<img src=\"https://i.imag.cx/HBf0H.gif\" data-thumbnail-src=\"https://i.lih.kg/thumbnail?u=https%3A%2F%2Fi.imag.cx%2FHBf0H.gif&h=6d3c54bb&s={SIZE}\" /><br />\n<br />\n好撚大包米<img src=\"/assets/faces/normal/bomb.gif\" class=\"hkgmoji\" />"},{"pid":"37c4d0a29cb0018157d63f893be530be6835ee76","tid":108737,"uid":49391,"like":0,"dislike":0,"score":0,"citedBy":0,"replyTime":"2017-02-05T13:06:48.000Z","msg":"<img src=\"https://i.imag.cx/HBLtV.gif\" data-thumbnail-src=\"https://i.lih.kg/thumbnail?u=https%3A%2F%2Fi.imag.cx%2FHBLtV.gif&h=df0cb6b0&s={SIZE}\" /><br />\n<br />\n<br />\n<br />\n<img src=\"https://i.imag.cx/HBeFq.gif\" data-thumbnail-src=\"https://i.lih.kg/thumbnail?u=https%3A%2F%2Fi.imag.cx%2FHBeFq.gif&h=9f301db1&s={SIZE}\" />"},{"pid":"1f6dc25155e8b011793a6d429719b1199d9555f7","tid":108737,"uid":49391,"like":0,"dislike":0,"score":0,"citedBy":0,"replyTime":"2017-02-05T13:07:06.000Z","msg":"<img src=\"https://i.imag.cx/HBk7x.gif\" data-thumbnail-src=\"https://i.lih.kg/thumbnail?u=https%3A%2F%2Fi.imag.cx%2FHBk7x.gif&h=796ee1bf&s={SIZE}\" /><br />\n<br />\n<br />\n<br />\n<img src=\"https://i.imag.cx/HBQR2.gif\" data-thumbnail-src=\"https://i.lih.kg/thumbnail?u=https%3A%2F%2Fi.imag.cx%2FHBQR2.gif&h=a816e980&s={SIZE}\" />"},{"pid":"e7ae413777fa57513885fceb6c493b305a6f1772","tid":108737,"uid":76098,"like":0,"dislike":0,"score":0,"citedBy":0,"replyTime":"2017-02-05T16:33:59.000Z","msg":"訓左未?"},{"pid":"f1c4276f769987d3f383a4c059a5a3c7473c65d5","tid":108737,"uid":76098,"like":0,"dislike":0,"score":0,"citedBy":0,"replyTime":"2017-02-05T16:36:35.000Z","msg":"j黎j去都係發覺呢d唔露既片最好睇"}]}