{"tid":1814025,"cid":13,"subCid":0,"title":"睇下你條Uniqlo褲嘅後備鈕攞咗出嚟未","createTime":"2020-01-06T16:44:38.000Z","updateTime":"2020-01-07T01:38:21.000Z","uid":78141,"like":0,"dislike":1,"uniUserReply":7,"replies":[{"pid":"b67e39e66ab33fed6620e1eb17164b58b86a12d7","tid":1814025,"uid":78141,"like":0,"dislike":0,"score":0,"citedBy":0,"replyTime":"2020-01-06T16:44:38.000Z","msg":"喺後面左邊褲袋，啱啱摸到先發現，之後睇埋其他褲，總共搵到7粒<br />\nDLLM邊個諗到收埋喺咁隱蔽嘅地方<img src=\"/assets/faces/normal/clown.gif\" class=\"hkgmoji\" />"},{"pid":"ba8103ce684805856a116c0ea0eb78c5d973964d","tid":1814025,"uid":39551,"like":0,"dislike":0,"score":0,"citedBy":0,"replyTime":"2020-01-06T16:47:31.000Z","msg":"一早知啦<img src=\"/assets/faces/pig/heard.gif\" class=\"hkgmoji\" />"},{"pid":"0729597aafff0b72aabde108a6f63b3238917fff","tid":1814025,"uid":192409,"like":0,"dislike":11,"score":-11,"citedBy":1,"replyTime":"2020-01-06T16:50:15.000Z","msg":"毒撚先着U記<img src=\"/assets/faces/pig/mock.gif\" class=\"hkgmoji\" />"},{"pid":"5d2b5a0fe3ab77653ddfdb6b5a1323a9201984e4","tid":1814025,"uid":38904,"like":0,"dislike":3,"score":-3,"citedBy":0,"replyTime":"2020-01-06T16:52:24.000Z","msg":"太cheap冇着過<img src=\"/assets/faces/pig/heard.gif\" class=\"hkgmoji\" />"},{"pid":"6893b5cef2b40930375f9b15efbb02b669c3bdb7","tid":1814025,"uid":62557,"like":0,"dislike":0,"score":0,"citedBy":0,"replyTime":"2020-01-06T17:02:25.000Z","msg":"<img src=\"/assets/faces/pig/mock.gif\" class=\"hkgmoji\" /><img src=\"/assets/faces/pig/mock.gif\" class=\"hkgmoji\" />"},{"pid":"7e8000f02290195d83d3a468dc2842e859020e2b","tid":1814025,"uid":277054,"like":0,"dislike":0,"score":0,"citedBy":0,"replyTime":"2020-01-06T17:03:04.000Z","msg":"<span style=\"font-size: xx-large;\"><div style=\"text-align: center;\"><br />\n1月8日 星期三<br />\n齊齊去幫襯<br />\n<a href=\"https://lih.kg/1813301\" data-auto-link target=\"_blank\">https://lih.kg/1813301</a><br />\n</div></span>"},{"pid":"c010f349c6eabd8ed5a4e127a31a3cff09dff663","tid":1814025,"uid":37524,"like":1,"dislike":0,"score":1,"quote":{"pid":"0729597aafff0b72aabde108a6f63b3238917fff","tid":1814025,"uid":192409,"like":0,"dislike":11,"score":-11,"citedBy":1,"replyTime":"2020-01-06T16:50:15.000Z","msg":"毒撚先着U記<img src=\"/assets/faces/pig/mock.gif\" class=\"hkgmoji\" />"},"citedBy":0,"replyTime":"2020-01-07T01:38:21.000Z","msg":"咁你著開咩牌子咁高級呀<br />\n講嚟聽吓好喎"}]}