{"tid":1962246,"cid":5,"subCid":0,"title":"新聞話政府會全數資助校巴褓姆車司機全數出糧，係咪on9架？","createTime":"2020-04-07T10:44:36.000Z","updateTime":"2020-04-07T15:03:46.000Z","uid":73991,"like":2,"dislike":1,"uniUserReply":9,"replies":[{"pid":"41a7021fc0fa4fea49e760dc6ccd01ca2f0a9c61","tid":1962246,"uid":73991,"like":0,"dislike":0,"score":0,"citedBy":1,"replyTime":"2020-04-07T10:44:36.000Z","msg":"即係唔洗做都有糧出，仲要大部份都藍到仆街<img src=\"/assets/faces/normal/fuck.gif\" class=\"hkgmoji\" />"},{"pid":"1144e62e2079d57e428451de8c5d295a95c1c937","tid":1962246,"uid":334796,"like":0,"dislike":0,"score":0,"citedBy":0,"replyTime":"2020-04-07T10:53:53.000Z","msg":"Source?"},{"pid":"e8d3d5b81da340e975ac27a1f100bd5947fbd3ef","tid":1962246,"uid":53026,"like":0,"dislike":0,"score":0,"citedBy":0,"replyTime":"2020-04-07T11:10:45.000Z","msg":"支那車？"},{"pid":"0f0e097bfd97a9ace04da548c7d6c8ccec8256e3","tid":1962246,"uid":9193,"like":1,"dislike":0,"score":1,"citedBy":0,"replyTime":"2020-04-07T11:11:20.000Z","msg":"巴士司機 的士司機呢"},{"pid":"7e7e26a165de3441f5ffc4d2a0b4995df7a58edc","tid":1962246,"uid":28114,"like":0,"dislike":0,"score":0,"quote":{"pid":"41a7021fc0fa4fea49e760dc6ccd01ca2f0a9c61","tid":1962246,"uid":73991,"like":0,"dislike":0,"score":0,"citedBy":1,"replyTime":"2020-04-07T10:44:36.000Z","msg":"即係唔洗做都有糧出，仲要大部份都藍到仆街<img src=\"/assets/faces/normal/fuck.gif\" class=\"hkgmoji\" />"},"citedBy":0,"replyTime":"2020-04-07T11:13:18.000Z","msg":"最大果間叫冠忠，深藍黎<img src=\"/assets/faces/normal/bye.gif\" class=\"hkgmoji\" />"},{"pid":"4286a6ae587196624a7078684bbf7f6090f49349","tid":1962246,"uid":178875,"like":0,"dislike":0,"score":0,"citedBy":0,"replyTime":"2020-04-07T11:14:46.000Z","msg":"買票"},{"pid":"2a2726089150792fe13d47668e73f21f7b0d1bfd","tid":1962246,"uid":39268,"like":1,"dislike":0,"score":1,"citedBy":0,"replyTime":"2020-04-07T11:14:47.000Z","msg":"香港政府真係痴撚線<br />\n幫人出糧"},{"pid":"22155d7e0b560e707306d38e2ef61e3c8c3e2967","tid":1962246,"uid":196924,"like":0,"dislike":0,"score":0,"citedBy":1,"replyTime":"2020-04-07T11:20:34.000Z","msg":"之前咪俾咗每架校巴2萬銀津貼<img src=\"/assets/faces/normal/clown.gif\" class=\"hkgmoji\" />"},{"pid":"33ad8c94427f0d7c2f6f7abd4f3b23200943a588","tid":1962246,"uid":79410,"like":0,"dislike":0,"score":0,"quote":{"pid":"22155d7e0b560e707306d38e2ef61e3c8c3e2967","tid":1962246,"uid":196924,"like":0,"dislike":0,"score":0,"citedBy":1,"replyTime":"2020-04-07T11:20:34.000Z","msg":"之前咪俾咗每架校巴2萬銀津貼<img src=\"/assets/faces/normal/clown.gif\" class=\"hkgmoji\" />"},"citedBy":0,"replyTime":"2020-04-07T15:03:46.000Z","msg":"仲要象徵式100蚊租停車場<img src=\"/assets/faces/normal/dead.gif\" class=\"hkgmoji\" />"}]}