{"tid":2269726,"cid":15,"subCid":0,"title":"麵咪媽上蘋果","createTime":"2020-11-03T15:16:17.000Z","updateTime":"2020-11-03T17:51:47.000Z","uid":252078,"like":45,"dislike":1,"uniUserReply":19,"replies":[{"pid":"ea487cf7040e4504cf9afa7be074b98aad964682","tid":2269726,"uid":252078,"like":0,"dislike":0,"score":0,"citedBy":0,"replyTime":"2020-11-03T15:16:17.000Z","msg":"<img src=\"https://na.cx/i/FGVQ91w.jpg\" data-thumbnail-src=\"https://i.lih.kg/thumbnail?u=https%3A%2F%2Fna.cx%2Fi%2FFGVQ91w.jpg&h=4d74878e&s={SIZE}\" /><br />\n<img src=\"/assets/faces/lm2/haha.gif\" class=\"hkgmoji\" /><img src=\"/assets/faces/lm2/haha.gif\" class=\"hkgmoji\" /><img src=\"/assets/faces/lm2/haha.gif\" class=\"hkgmoji\" /><img src=\"/assets/faces/lm2/haha.gif\" class=\"hkgmoji\" /><img src=\"/assets/faces/lm2/haha.gif\" class=\"hkgmoji\" /><br />\n<br />\n<br />\n<br />\n<br />\n<br />\n<br />\n<br />\n<br />\n<br />\n<br />\n<br />\n<br />\nhello蘋果記者<img src=\"/assets/faces/normal/bye.gif\" class=\"hkgmoji\" /><img src=\"/assets/faces/normal/bye.gif\" class=\"hkgmoji\" /><img src=\"/assets/faces/normal/bye.gif\" class=\"hkgmoji\" />"},{"pid":"907168867f279db2fffc17ce153d64a2f8f3fbc4","tid":2269726,"uid":55955,"like":9,"dislike":0,"score":9,"citedBy":0,"replyTime":"2020-11-03T15:19:52.000Z","msg":"笑到，真係訪問專家咁<img src=\"/assets/faces/lm2/sosad.gif\" class=\"hkgmoji\" />"},{"pid":"b18cf25ef1d739f39e84165f01f684d06d41a248","tid":2269726,"uid":205105,"like":9,"dislike":0,"score":9,"citedBy":2,"replyTime":"2020-11-03T15:25:25.000Z","msg":"蘋果有麵神直線電話<img src=\"/assets/faces/normal/adore.gif\" class=\"hkgmoji\" /><img src=\"/assets/faces/normal/adore.gif\" class=\"hkgmoji\" />"},{"pid":"eca257f909fc03f00f79f75aed76e29cea30f38a","tid":2269726,"uid":252078,"like":4,"dislike":1,"score":3,"quote":{"pid":"b18cf25ef1d739f39e84165f01f684d06d41a248","tid":2269726,"uid":205105,"like":9,"dislike":0,"score":9,"citedBy":2,"replyTime":"2020-11-03T15:25:25.000Z","msg":"蘋果有麵神直線電話<img src=\"/assets/faces/normal/adore.gif\" class=\"hkgmoji\" /><img src=\"/assets/faces/normal/adore.gif\" class=\"hkgmoji\" />"},"citedBy":1,"replyTime":"2020-11-03T15:27:43.000Z","msg":"<img src=\"/assets/faces/normal/adore.gif\" class=\"hkgmoji\" /><img src=\"/assets/faces/normal/adore.gif\" class=\"hkgmoji\" /><img src=\"/assets/faces/normal/adore.gif\" class=\"hkgmoji\" /><img src=\"/assets/faces/normal/adore.gif\" class=\"hkgmoji\" /><img src=\"/assets/faces/normal/adore.gif\" class=\"hkgmoji\" /><br />\n接受蘋果訪問"},{"pid":"aa4dbcce61b51b11d53604a3fb1f178ac4f07844","tid":2269726,"uid":42881,"like":7,"dislike":0,"score":7,"citedBy":0,"replyTime":"2020-11-03T15:29:10.000Z","msg":"佢又冇抽又冇孖展，只係口講，連手續費都冇蝕就燈得死蟻<br />\n<br />\n<br />\n我聽日係唔係應該ALL IN匯豐?<img src=\"/assets/faces/lm2/lightbulb.gif\" class=\"hkgmoji\" />"},{"pid":"df2c2db34d59b7e2b5673c2668af3d81ac92255a","tid":2269726,"uid":214173,"like":0,"dislike":0,"score":0,"citedBy":0,"replyTime":"2020-11-03T15:37:06.000Z","msg":"麵咪媽既威力可以被封為新代股壇毒藥<img src=\"/assets/faces/normal/sosad.gif\" class=\"hkgmoji\" />"},{"pid":"ab4f4c6dc6e312ffdcfd7cfc660e891d8117add0","tid":2269726,"uid":318557,"like":0,"dislike":0,"score":0,"citedBy":0,"replyTime":"2020-11-03T15:37:31.000Z","msg":"<img src=\"/assets/faces/lm2/lightbulb.gif\" class=\"hkgmoji\" /><img src=\"/assets/faces/lm2/abomb.gif\" class=\"hkgmoji\" />"},{"pid":"06be9243d859e24e22e42ae48f867605920cdd4c","tid":2269726,"uid":155818,"like":1,"dislike":0,"score":1,"citedBy":0,"replyTime":"2020-11-03T15:37:51.000Z","msg":"我都唔知典算<img src=\"/assets/faces/normal/sosad.gif\" class=\"hkgmoji\" /><img src=\"/assets/faces/normal/sosad.gif\" class=\"hkgmoji\" />"},{"pid":"7f4894d6483bfd3606a5f604f8275d141119f67b","tid":2269726,"uid":101481,"like":3,"dislike":0,"score":3,"quote":{"pid":"eca257f909fc03f00f79f75aed76e29cea30f38a","tid":2269726,"uid":252078,"like":4,"dislike":1,"score":3,"quote":{"pid":"b18cf25ef1d739f39e84165f01f684d06d41a248","tid":2269726,"uid":205105,"like":9,"dislike":0,"score":9,"citedBy":2,"replyTime":"2020-11-03T15:25:25.000Z","msg":"蘋果有麵神直線電話<img src=\"/assets/faces/normal/adore.gif\" class=\"hkgmoji\" /><img src=\"/assets/faces/normal/adore.gif\" class=\"hkgmoji\" />"},"citedBy":1,"replyTime":"2020-11-03T15:27:43.000Z","msg":"<img src=\"/assets/faces/normal/adore.gif\" class=\"hkgmoji\" /><img src=\"/assets/faces/normal/adore.gif\" class=\"hkgmoji\" /><img src=\"/assets/faces/normal/adore.gif\" class=\"hkgmoji\" /><img src=\"/assets/faces/normal/adore.gif\" class=\"hkgmoji\" /><img src=\"/assets/faces/normal/adore.gif\" class=\"hkgmoji\" /><br />\n接受蘋果訪問"},"citedBy":0,"replyTime":"2020-11-03T15:39:02.000Z","msg":"連表情都可以知埋<img src=\"/assets/faces/normal/adore.gif\" class=\"hkgmoji\" /><img src=\"/assets/faces/normal/adore.gif\" class=\"hkgmoji\" /><img src=\"/assets/faces/normal/adore.gif\" class=\"hkgmoji\" />"},{"pid":"8d0e9b5c4aa8ccee27c4efac62e3584c49c6f17f","tid":2269726,"uid":85659,"like":0,"dislike":0,"score":0,"citedBy":0,"replyTime":"2020-11-03T15:39:30.000Z","msg":"<img src=\"/assets/faces/normal/adore.gif\" class=\"hkgmoji\" /><img src=\"/assets/faces/normal/adore.gif\" class=\"hkgmoji\" /><img src=\"/assets/faces/normal/adore.gif\" class=\"hkgmoji\" />"},{"pid":"0a73f3ae9fee4cf0ae090b9b6e3f5e4f09936fba","tid":2269726,"uid":104138,"like":0,"dislike":0,"score":0,"quote":{"pid":"b18cf25ef1d739f39e84165f01f684d06d41a248","tid":2269726,"uid":205105,"like":9,"dislike":0,"score":9,"citedBy":2,"replyTime":"2020-11-03T15:25:25.000Z","msg":"蘋果有麵神直線電話<img src=\"/assets/faces/normal/adore.gif\" class=\"hkgmoji\" /><img src=\"/assets/faces/normal/adore.gif\" class=\"hkgmoji\" />"},"citedBy":0,"replyTime":"2020-11-03T15:41:11.000Z","msg":"勁過四大富豪聯手"},{"pid":"4bbca779b5db5cef657e749bc3c8d8cd6905442c","tid":2269726,"uid":277186,"like":0,"dislike":0,"score":0,"citedBy":0,"replyTime":"2020-11-03T15:41:38.000Z","msg":"股市怒海中既燈塔<img src=\"/assets/faces/pig/wail.gif\" class=\"hkgmoji\" />"},{"pid":"5d43a88cf0d0ff430af8d6d49fbb602262c43f0e","tid":2269726,"uid":220359,"like":1,"dislike":0,"score":1,"citedBy":0,"replyTime":"2020-11-03T15:41:39.000Z","msg":"<img src=\"/assets/faces/lm2/lightbulb.gif\" class=\"hkgmoji\" />媽咪麵有冇諗過去做財演？實爆view rate"},{"pid":"09982fff189d15c3e5e7e1151043f73410cbc9b4","tid":2269726,"uid":44638,"like":0,"dislike":0,"score":0,"citedBy":0,"replyTime":"2020-11-03T15:42:47.000Z","msg":"TENET<img src=\"/assets/faces/normal/sosad.gif\" class=\"hkgmoji\" />"},{"pid":"b7282f0d803d83881f6e95a268660d6f83f0dcd5","tid":2269726,"uid":261522,"like":0,"dislike":0,"score":0,"citedBy":0,"replyTime":"2020-11-03T15:43:49.000Z","msg":"<img src=\"/assets/faces/dog/cry.gif\" class=\"hkgmoji\" /> 典算<img src=\"/assets/faces/big/lomore_shocking.gif\" class=\"hkgmoji\" /><img src=\"/assets/faces/big/lomore_shocking.gif\" class=\"hkgmoji\" /><img src=\"/assets/faces/big/lomore_shocking.gif\" class=\"hkgmoji\" />"},{"pid":"c4a3834c7c748b75479162baf0e23619ffa5297c","tid":2269726,"uid":126226,"like":1,"dislike":0,"score":1,"citedBy":1,"replyTime":"2020-11-03T16:04:16.000Z","msg":"我都唔知點算 <img src=\"/assets/faces/lm2/noodles.gif\" class=\"hkgmoji\" /><img src=\"/assets/faces/lm2/noodles.gif\" class=\"hkgmoji\" /><img src=\"/assets/faces/lm2/noodles.gif\" class=\"hkgmoji\" />"},{"pid":"1d726534d8377e5ff0d46295b65be1f11ebdd9a2","tid":2269726,"uid":128716,"like":0,"dislike":0,"score":0,"citedBy":0,"replyTime":"2020-11-03T16:51:47.000Z","msg":"個一字眼icon畫龍點睛<img src=\"/assets/faces/lm2/haha.gif\" class=\"hkgmoji\" />"},{"pid":"8e338903aa0c87aea76196704478e8721f5e47bb","tid":2269726,"uid":316420,"like":0,"dislike":0,"score":0,"quote":{"pid":"c4a3834c7c748b75479162baf0e23619ffa5297c","tid":2269726,"uid":126226,"like":1,"dislike":0,"score":1,"citedBy":1,"replyTime":"2020-11-03T16:04:16.000Z","msg":"我都唔知點算 <img src=\"/assets/faces/lm2/noodles.gif\" class=\"hkgmoji\" /><img src=\"/assets/faces/lm2/noodles.gif\" class=\"hkgmoji\" /><img src=\"/assets/faces/lm2/noodles.gif\" class=\"hkgmoji\" />"},"citedBy":0,"replyTime":"2020-11-03T17:07:46.000Z","msg":"<img src=\"/assets/faces/dog/haha.gif\" class=\"hkgmoji\" /><img src=\"/assets/faces/dog/haha.gif\" class=\"hkgmoji\" /><img src=\"/assets/faces/dog/haha.gif\" class=\"hkgmoji\" />佢同連燈仔好似唔係咁講"},{"pid":"a47679efa5bbf468a605a36af9e73f722d228a54","tid":2269726,"uid":309664,"like":0,"dislike":0,"score":0,"citedBy":0,"replyTime":"2020-11-03T17:19:33.000Z","msg":"麵麵好野<img src=\"/assets/faces/lm2/lightbulb.gif\" class=\"hkgmoji\" />"},{"pid":"630c6692f8cafb73c0ba858f7d40eb889f220a24","tid":2269726,"uid":132941,"like":0,"dislike":0,"score":0,"citedBy":0,"replyTime":"2020-11-03T17:51:47.000Z","msg":"輕鬆<img src=\"/assets/faces/normal/slick.gif\" class=\"hkgmoji\" />"}]}