{"tid":281267,"cid":1,"subCid":0,"title":"瞓喺張床。。。","createTime":"2017-06-12T14:54:50.000Z","updateTime":"2017-06-12T14:55:39.000Z","uid":89985,"like":0,"dislike":0,"uniUserReply":0,"replies":[{"pid":"0496ae7ccb3a9bd1b22eb80c72fec3e2a183df51","tid":281267,"uid":89985,"like":0,"dislike":0,"score":0,"citedBy":0,"replyTime":"2017-06-12T14:54:50.000Z","msg":"一唔小心 部手機 ...<br />\n<br />\n啪 的一聲<br />\n<br />\n<br />\n<br />\n<br />\n<img src=\"/assets/faces/fs/angel.gif\" class=\"hkgmoji\" />我塊面扁左"},{"pid":"e47e51464af7155ce47a63fae182055f907b3030","tid":281267,"uid":89985,"like":0,"dislike":0,"score":0,"citedBy":0,"replyTime":"2017-06-12T14:55:39.000Z","msg":"<img src=\"/assets/faces/fs/angel.gif\" class=\"hkgmoji\" />塊面凸唔返 點撚算好"}]}