{"tid":585826,"cid":5,"subCid":0,"title":"習近平是上帝興起的一代明君 耶穌再來","createTime":"2018-03-09T04:07:20.000Z","updateTime":"2018-03-09T04:21:12.000Z","uid":3393,"like":8,"dislike":1,"uniUserReply":4,"replies":[{"pid":"0fd3074107afcd0c5c7fb671e9f767e2192f00d8","tid":585826,"uid":3393,"like":0,"dislike":0,"score":0,"citedBy":0,"replyTime":"2018-03-09T04:07:20.000Z","msg":"<img src=\"http://blog.creaders.net/upfile/image/20150105/20150105202625_88247.jpg\" data-thumbnail-src=\"https://i.lih.kg/thumbnail?u=http%3A%2F%2Fblog.creaders.net%2Fupfile%2Fimage%2F20150105%2F20150105202625_88247.jpg&h=26f5621f&s={SIZE}\" /><br />\n<br />\n為了令中梵「行埋」，教廷似乎已跟中共達成協議：不但同意任命七位中共欽點的非法主教，更勸退兩位教廷認可的合法主教。這樣的交易，算不算出賣教會呢？<br />\n<br />\n我想起《鋼之鍊金術師》的利奧爾城。利奧爾人信奉雷特教，教主能行神跡，但主角艾力克兄弟發現，教主異能並非來自真神，他只是依賴人造人給他的假賢者之石，運用鍊金術冒充神跡而已。更深層的真相是：雷特教一直受人造人和幕後大boss「父親大人」操控，作用是思想控制利奧爾人，協助父親大人圓他的「上帝夢」。艾力克兄弟當眾撕破教主的假面具後，人造人見他失去價值，暗中把他斃了，索性自己化身教主，繼續經營雷特教。利奧爾人跟我們一樣，非常善忘，亦十分需要宗教這精神鴉片，所以不但沒懷疑教主是假的，甚至覺得「假貨比真貨好」。<br />\n<br />\n《鋼鍊》世界跟我們的現實很相似，也許就如03年動畫版所說，兩個世界是平行宇宙，中間只隔了一道真理之門。真的主教DQ了又如何，父親大人，不，阿爺欽點的不是更強大嗎？從一般信眾的角度看，兩者毫無分別──即使有，也是象徵七宗罪的七主教更威武吧。教廷只是勸退兩個主教，接受七位「人造主教」，就可在中國大開天堂之門，而中國也可抓緊機遇發展「一帶天路」，簡直是win-win。當然，中國天主教的教義或要微調，試看佛教。<br />\n<br />\n<span style=\"font-size: small;\"><span style=\"color: red;\">大陸高僧早說，「十九大報告是當代的佛經」（印順大和尚語）</span></span>，<span style=\"font-size: small;\"><span style=\"color: red;\">「習近平是菩薩再來」（淨空法師語）</span></span>。日後神父會否宣佈「習近平是耶穌再來」呢？難說。但為了擴大鳥籠，至少也要把《主禱文》中國化，變成：<br />\n「我們的大大，願祢的名受顯揚，願祢的黨降臨，願祢的旨意奉行在民間，如同在中央。求祢今天賞給我們維穩的食糧，求祢寬恕我們的罪過，如同我們寬恕別人一樣。不要讓我們陷於港獨，但救我們移民西方。亞孟。」  <br />\n<br />\n馮睎乾 <br />\n<a href=\"http://bbs.creaders.net/history/bbsviewer.php?trd_id=1020910&amp;language=big5\" data-sr-url=\"https://r.lihkg.com/link?u=http%3A%2F%2Fbbs.creaders.net%2Fhistory%2Fbbsviewer.php%3Ftrd_id%3D1020910%26language%3Dbig5&d=gyCP5LXbMBRKp12G2vGD8JUWI6eGpREPWAa3TRi9Bo4%3D&h=caebc839\" target=\"_blank\">http://bbs.creaders.net/history/bbsviewer.php?trd_id=1020910&amp;language=big5</a><br />\n<a href=\"https://hk.lifestyle.appledaily.com/lifestyle/columnist/%E9%A6%AE%E7%9D%8E%E4%B9%BE/daily/article/20180205/20295215\" data-sr-url=\"https://r.lihkg.com/link?u=https%3A%2F%2Fhk.lifestyle.appledaily.com%2Flifestyle%2Fcolumnist%2F%25E9%25A6%25AE%25E7%259D%258E%25E4%25B9%25BE%2Fdaily%2Farticle%2F20180205%2F20295215&d=gyCP5LXbMBRKp12G2vGD8JUWI6eGpREPWAa3TRi9Bo4%3D&h=37e6a495\" data-ef-url=\"https://embed.lih.kg/frame?u=https%3A%2F%2Fhk.lifestyle.appledaily.com%2Flifestyle%2Fcolumnist%2F%25E9%25A6%25AE%25E7%259D%258E%25E4%25B9%25BE%2Fdaily%2Farticle%2F20180205%2F20295215&h=799c9f93\" target=\"_blank\">https://hk.lifestyle.appledaily.com/lifestyle/columnist/%E9%A6%AE%E7%9D%8E%E4%B9%BE/daily/article/20180205/20295215</a>"},{"pid":"e8bf712d10799be3023def1cf79705d9348ad026","tid":585826,"uid":32723,"like":0,"dislike":0,"score":0,"citedBy":0,"replyTime":"2018-03-09T04:16:41.000Z","msg":"習大大是我皇萬歲萬歲歲"},{"pid":"fedc3fdf1f87852a14e2c2ecaff7b3fd5e2755d8","tid":585826,"uid":98317,"like":3,"dislike":0,"score":3,"citedBy":0,"replyTime":"2018-03-09T04:19:10.000Z","msg":"Ive civil fg 月入25k up"},{"pid":"8ad8070f25b1c2c55ee393e94b990e0185d4f27b","tid":585826,"uid":37735,"like":0,"dislike":0,"score":0,"citedBy":0,"replyTime":"2018-03-09T04:21:12.000Z","msg":"堆宗教全部都係垃圾<br />\n<br />\n點叫人信<img src=\"/assets/faces/lomoji/04.png\" class=\"hkgmoji\" />"}]}