{"tid":704628,"cid":6,"subCid":0,"title":"其實美斯只係一個技術好好既球員","createTime":"2018-06-16T14:41:20.000Z","updateTime":"2018-06-16T15:00:40.000Z","uid":27485,"like":54,"dislike":2,"uniUserReply":12,"replies":[{"pid":"ab9895681512bddad91337d2d9b803d4ce121067","tid":704628,"uid":27485,"like":0,"dislike":0,"score":0,"citedBy":0,"replyTime":"2018-06-16T14:41:20.000Z","msg":"你話要佢帶起一隊波<br />\n係冇乜可能"},{"pid":"011069d860e46a878d97db195f216a7f67fb99e5","tid":704628,"uid":141789,"like":1,"dislike":2,"score":-1,"citedBy":3,"replyTime":"2018-06-16T14:46:10.000Z","msg":"好似旨意曬佢咁 技術好就要有咁大責任嘅咩"},{"pid":"7c8a0e8bd88249e45ebc82312e659fddf4a84295","tid":704628,"uid":69568,"like":0,"dislike":0,"score":0,"citedBy":0,"replyTime":"2018-06-16T14:46:28.000Z","msg":"樓豬做咩直線<img src=\"/assets/faces/normal/cry.gif\" class=\"hkgmoji\" /> <img src=\"/assets/faces/normal/cry.gif\" class=\"hkgmoji\" />"},{"pid":"2c61d044c8c3f6247162cc393fff0a2a13da663b","tid":704628,"uid":143454,"like":0,"dislike":0,"score":0,"citedBy":0,"replyTime":"2018-06-16T14:54:50.000Z","msg":"此回覆已被刪除"},{"pid":"660a563f1e9b5c5f509e64ab57132f5f3a480cee","tid":704628,"uid":21255,"like":0,"dislike":1,"score":-1,"quote":{"pid":"011069d860e46a878d97db195f216a7f67fb99e5","tid":704628,"uid":141789,"like":1,"dislike":2,"score":-1,"citedBy":3,"replyTime":"2018-06-16T14:46:10.000Z","msg":"好似旨意曬佢咁 技術好就要有咁大責任嘅咩"},"citedBy":0,"replyTime":"2018-06-16T14:55:32.000Z","msg":"兩三個夾都照俾<img src=\"/assets/faces/normal/sosad.gif\" class=\"hkgmoji\" /><br />\n明明其他隊友好空"},{"pid":"525dc10eb55b4b90604d0c258d35fadaba3ff2a8","tid":704628,"uid":37297,"like":0,"dislike":0,"score":0,"quote":{"pid":"011069d860e46a878d97db195f216a7f67fb99e5","tid":704628,"uid":141789,"like":1,"dislike":2,"score":-1,"citedBy":3,"replyTime":"2018-06-16T14:46:10.000Z","msg":"好似旨意曬佢咁 技術好就要有咁大責任嘅咩"},"citedBy":0,"replyTime":"2018-06-16T14:56:51.000Z","msg":"咁就唔好話係球王啦"},{"pid":"100ef3ef4f0463a492b40a1bedcc73a75e8c7215","tid":704628,"uid":15302,"like":1,"dislike":0,"score":1,"citedBy":0,"replyTime":"2018-06-16T14:57:09.000Z","msg":"近年真係比阿朗比下去"},{"pid":"59f66917627e326a4038698dfbe14b4ce434aefe","tid":704628,"uid":72677,"like":0,"dislike":0,"score":0,"quote":{"pid":"011069d860e46a878d97db195f216a7f67fb99e5","tid":704628,"uid":141789,"like":1,"dislike":2,"score":-1,"citedBy":3,"replyTime":"2018-06-16T14:46:10.000Z","msg":"好似旨意曬佢咁 技術好就要有咁大責任嘅咩"},"citedBy":0,"replyTime":"2018-06-16T14:57:11.000Z","msg":"但係隊長wo"},{"pid":"3167d61133d164247d783320c3ecf98d81f1e9f3","tid":704628,"uid":32051,"like":0,"dislike":0,"score":0,"citedBy":0,"replyTime":"2018-06-16T14:57:37.000Z","msg":"小花<img src=\"/assets/faces/dog/smile.gif\" class=\"hkgmoji\" /> <img src=\"/assets/faces/dog/hehe.gif\" class=\"hkgmoji\" />"},{"pid":"e934cb0893ba196f69950ceb1b9fd3897cdd4d37","tid":704628,"uid":5190,"like":0,"dislike":0,"score":0,"citedBy":0,"replyTime":"2018-06-16T14:57:53.000Z","msg":"牙朗都一個對11個啦"},{"pid":"26108468d27ba17d0c3b4798dde3801af40beef2","tid":704628,"uid":83933,"like":1,"dislike":0,"score":1,"citedBy":0,"replyTime":"2018-06-16T14:59:44.000Z","msg":"講真，阿朗同小花嘅表現真係高下立見。當球隊需要你嘅時候，就要變，睇到阿朗尋日由係前場等波打反擊，去到開始返中場幫波，甚至自己嘗試突破搵機會，唔同方法都去試。反觀美斯就真係等運到，連最叻嘅突破都懶得去做，行行企企，一拎波一係亂射一係就夾硬質比個前鋒<img src=\"/assets/faces/normal/sosad.gif\" class=\"hkgmoji\" />"},{"pid":"a348feccc37fa3a7e37e4b85f5b267fa1e822356","tid":704628,"uid":1009,"like":1,"dislike":0,"score":1,"citedBy":0,"replyTime":"2018-06-16T15:00:40.000Z","msg":"唔好吹撚到咩歷史級球王啦，施丹淨係決賽一腳楣底入十二碼收死保方都屌打你小花啦<img src=\"/assets/faces/normal/sosad.gif\" class=\"hkgmoji\" />"}]}